<OverlayData>
    <MarkerCategory name="legs" DisplayName="Lady Elyssa's Guides " texture="Data/LadyElyssa/Images/trailarrow.png" animSpeed="1" alpha="0.9" fadeNear="3000" fadeFar="4000" mapDisplaySize="10" mapVisibility="1">
        <!-- MAP COMPLETION -->
        <MarkerCategory name="map" DisplayName="Map Completion" miniMapVisibility="0" mapVisibility="1" mapDisplaySize="10">
            <MarkerCategory name="voe" DisplayName="Visions of Eternity (WIP)">
                
                <MarkerCategory name="map" IsSeparator="1" DisplayName="MAP ZONE"/>
                
                <MarkerCategory name="ss" DisplayName="Shipwreck Strand">
                    <MarkerCategory name="set" IsSeparator="1" DisplayName="SETTINGS"/>
                    <MarkerCategory name="start" DisplayName="Toggle Start Marker" iconFile="Data/LadyElyssa/Images/Start.png" inGameVisibility="0" miniMapVisibility="1" mapDisplaySize="128"/>
                    <MarkerCategory name="heartinfo" DisplayName="Toggle Heart Info" iconFile="Data/LadyElyssa/Images/Icons/Blank.png"/>
                    <MarkerCategory name="heartpath" DisplayName="Toggle Heart Trails" texture="Data/LadyElyssa/Images/Line - Heart.png" animSpeed="0"  color="FFFF00"/>
                    <MarkerCategory name="glider" DisplayName="Glider" iconFile="Data/LadyElyssa/Images/Icons/Glider.png" iconSize="0.5"/>
                    <MarkerCategory name="mount" DisplayName="Mounts" miniMapVisibility="0" minSize="32" maxSize="48">
                        <MarkerCategory name="beetle" DisplayName="Beetle" iconFile="Data/LadyElyssa/Images/Mounts/Mount_Beetle.png"/>
                        <MarkerCategory name="skimmer" DisplayName="Skimmer" iconFile="Data/LadyElyssa/Images/Mounts/Mount_Skimmer.png"/>
                        <MarkerCategory name="skyscale" DisplayName="Skyscale" iconFile="Data/LadyElyssa/Images/Mounts/Mount_Skyscale.png"/>
                        <MarkerCategory name="springer" DisplayName="Springer" iconFile="Data/LadyElyssa/Images/Mounts/Mount_Springer.png"/>
                    </MarkerCategory>
                    <!-- End Mounts -->
                </MarkerCategory>

                <MarkerCategory name="sw" DisplayName="Starlit Weald">
                <MarkerCategory name="set" IsSeparator="1" DisplayName="SETTINGS"/>
                <MarkerCategory name="start" DisplayName="Toggle Start Marker" iconFile="Data/LadyElyssa/Images/Start.png" inGameVisibility="0" miniMapVisibility="1" mapDisplaySize="128"/>
                <MarkerCategory name="glider" DisplayName="Glider" iconFile="Data/LadyElyssa/Images/Icons/Glider.png" iconSize="0.5"/>
                <MarkerCategory name="heartinfo" DisplayName="Toggle Heart Info" iconFile="Data/LadyElyssa/Images/Icons/Blank.png"/>
                <MarkerCategory name="heartpath" DisplayName="Toggle Heart Trails" texture="Data/LadyElyssa/Images/Line - Heart.png" animSpeed="0"/>
                    <MarkerCategory name="mount" DisplayName="Mounts" miniMapVisibility="0" minSize="32" maxSize="48">
                        <MarkerCategory name="beetle" DisplayName="Beetle" iconFile="Data/LadyElyssa/Images/Mounts/Mount_Beetle.png"/>
                        <MarkerCategory name="skimmer" DisplayName="Skimmer" iconFile="Data/LadyElyssa/Images/Mounts/Mount_Skimmer.png"/>
                        <MarkerCategory name="skyscale" DisplayName="Skyscale" iconFile="Data/LadyElyssa/Images/Mounts/Mount_Skyscale.png"/>
                        <MarkerCategory name="springer" DisplayName="Springer" iconFile="Data/LadyElyssa/Images/Mounts/Mount_Springer.png"/>
                    </MarkerCategory>
                    <!-- End Mounts -->
                    <MarkerCategory name="trail" DisplayName="Trail Segment">
                        <MarkerCategory name="1" DisplayName="One" iconFile="Data/LadyElyssa/Images/Numbers/1.png"/>
                        <MarkerCategory name="2" DisplayName="Two" iconFile="Data/LadyElyssa/Images/Numbers/2.png"/>
                    </MarkerCategory>
                </MarkerCategory>
            </MarkerCategory>
            <!-- END JW MAP COMPLETION -->
        </MarkerCategory>
        <!-- MAP COMPLETION -->
    </MarkerCategory>
    <!-- End of Lady Elyssa's Guides -->
</OverlayData>
