<OverlayData>
    <POIs>
        <!-- Mastery Insights -->

        <!-- Lowland Shore -->
        <POI MapID="1550" xpos="550.979" ypos="423.069" zpos="-554.113" type="legs.mastery.jwmp.ls.start" GUID="rqzOpumDpUCnA+Fs71AgAw=="/>
        <Trail type="legs.mastery.jwmp.ls" trailData="Data/LadyElyssa/Mastery Insights/JW/Mastery Insights - Lowland Shore 1.trl" color="2742B9"/>
        <Trail type="legs.mastery.jwmp.ls" trailData="Data/LadyElyssa/Mastery Insights/JW/Mastery Insights - Lowland Shore 2.trl" color="2742B9"/>
        <Trail type="legs.mastery.jwmp.ls" trailData="Data/LadyElyssa/Mastery Insights/JW/Mastery Insights - Lowland Shore 3.trl" color="2742B9"/>
        <Trail type="legs.mastery.jwmp.ls" trailData="Data/LadyElyssa/Mastery Insights/JW/Mastery Insights - Lowland Shore 4.trl" color="2742B9"/>
        <POI MapID="1550" xpos="575.6" ypos="85.6191" zpos="504.985" type="legs.mastery.jwmp.ls.wp" GUID="CR6x0cKqv0mXXHb/11RabA==" copy="[&BK4OAAA=]" copy-message="Harvest Den Waypoint"/>
        <POI MapID="1550" xpos="-329.088" ypos="203.89" zpos="425.738" type="legs.mastery.jwmp.ls.wp" GUID="ga69vN0ukUWSrTotjCN7Yw==" copy=" [&BMkOAAA=]" copy-message="Hot Springs Waypoint"/>
        <POI MapID="1550" xpos="-514.773" ypos="247.935" zpos="-301.243" type="legs.mastery.jwmp.ls.wp" GUID="k7sfJsw/jUKX/GO/I8HRHw==" copy=" [&BPsOAAA=]" copy-message="Journeykin Outpost Waypoint"/>

        <!-- Janthir Syntri -->
        <Trail type="legs.mastery.jwmp.js" trailData="Data/LadyElyssa/Mastery Insights/JW/Mastery Insights - Janthir Syntri 1.trl" color="2742B9"/>
        <Trail type="legs.mastery.jwmp.js" trailData="Data/LadyElyssa/Mastery Insights/JW/Mastery Insights - Janthir Syntri 2.trl" color="2742B9"/>
        <Trail type="legs.mastery.jwmp.js" trailData="Data/LadyElyssa/Mastery Insights/JW/Mastery Insights - Janthir Syntri 3.trl" color="2742B9"/>
        <Trail type="legs.mastery.jwmp.js" trailData="Data/LadyElyssa/Mastery Insights/JW/Mastery Insights - Janthir Syntri 4.trl" color="2742B9"/>
        <Trail type="legs.mastery.jwmp.js" trailData="Data/LadyElyssa/Mastery Insights/JW/Mastery Insights - Janthir Syntri 5.trl" color="2742B9"/>
    </POIs>
</OverlayData>